MANIFEST.in
README.rst
setup.py
pybloom/__init__.py
pybloom/benchmarks.py
pybloom/pybloom.py
pybloom/tests.py
pybloom/utils.py
pybloom_mirror.egg-info/PKG-INFO
pybloom_mirror.egg-info/SOURCES.txt
pybloom_mirror.egg-info/dependency_links.txt
pybloom_mirror.egg-info/requires.txt
pybloom_mirror.egg-info/top_level.txt
pybloom_mirror.egg-info/zip-safe